{"html_index.md":"BAF_-fHP","css_index.md":"BssBSO3B","css_盒模型.md":"B_1xZi4h","ai_cursor.md":"CpeQGfph","css_linear-gradient.md":"C7_gYps1","html_元信息类标签.md":"NIDFUSfd","css_bfc.md":"Cu6Lj2Hy","css_移动端1px.md":"CsCtWRYN","ai_index.md":"dRPWmrOX","css_波浪悬浮球.md":"75BUY5hS","javascript_call-apply-bind.md":"BkZAVzkG","javascript_new.md":"BeCccA8i","network_index.md":"CTptOWgA","typescript_index.md":"DJ66BsUI","network_tcp.md":"CGZKzG58","network_search-url.md":"_LlT6VaX","javascript_throttle.md":"BEHm_9nF","javascript_deepclone.md":"oK5rUrq9","javascript_index.md":"N-8Rw5rX","react_index.md":"D9fVZuM8","react_demo.md":"DjVmIMij","javascript_generator-async.md":"0YHv633D","network_http-status.md":"BOBH1rif","network_http-cache.md":"CjRbPt9C","vite_index.md":"k2k5rksA","vue_minio.md":"BNlaWNyd","javascript_instanceof.md":"DuZe1pcg","vue_index.md":"B2KrOzZK","typescript_notes.md":"ClUBlnFq","vue_directive.md":"C-AxfYQs","javascript_promise.md":"K9KZnpmJ","javascript_extends.md":"JZeR96T0","vue_axios.md":"DTbqfB2R","vue_表格拖拽.md":"vAKrFKwZ","about_index.md":"B1jJ37JI","vue_分环境打包.md":"Dwktfu2E","vue_virtual-list.md":"CrpL5IBf","algorithm_algo_object-path-get.md":"eiMLZPUQ","algorithm_algo_compete-state.md":"5MsPUCMI","vue_配置切换多套主题色系.md":"DQc3uUW7","algorithm_algo_function-curry.md":"SqcV0eJx","algorithm_algo_list-and-tree.md":"Bqgcoo-_","vue_plugin.md":"Dxo-tUR8","javascript_数组.md":"Bt7hhKco","algorithm_algo_parallel-request.md":"Dhzl1GuV","algorithm_algo_publish-subscribe.md":"hwGLs-KM","tools_index.md":"Ct0U8dPr","index.md":"QhVF1dZE","essays_index.md":"BAyZiZxR","excellent-site_index.md":"D4UcGs_v","essays_四年一梦.md":"C8nyFQEu","algorithm_doubly-linked-list.md":"BSat0E1c","algorithm_linked-list.md":"Dvt70y01","vite_ssr.md":"740eZhGG"}
